image_preprocessing_comparison/__init__.py
image_preprocessing_comparison/compare_images.py
image_preprocessing_comparison/core.py
image_preprocessing_comparison/filters.py
image_preprocessing_comparison/test.py
image_preprocessing_comparison-1.1.1.dist-info/LICENSE
image_preprocessing_comparison-1.1.1.dist-info/METADATA
image_preprocessing_comparison-1.1.1.dist-info/WHEEL
image_preprocessing_comparison-1.1.1.dist-info/top_level.txt
image_preprocessing_comparison-1.1.1.dist-info/RECORD
