Metadata-Version: 2.1
Name: image_preprocessing_comparison
Version: 1.1.1
Summary: This Python library provides a comprehensive set of functions for image preprocessing and comparison. It includes various filters for image enhancement, as well as metrics for comparing images.
Home-page: https://github.com/vinodbaste/image_preprocessing_and_comparison/blob/main/Readme.md
Author: Vinod Baste
Author-email: bastevinod@gmail.com
License: MIT
Keywords: image preprocessing,image comparison
Classifier: Development Status :: 5 - Production/Stable
Classifier: Intended Audience :: Education
Classifier: Operating System :: OS Independent
Classifier: License :: OSI Approved :: MIT License
Classifier: Programming Language :: Python :: 3
Requires-Python: >=3.6
License-File: LICENSE
